clappia_tools/__init__.py
clappia_tools/_enums/__init__.py
clappia_tools/_enums/enums.py
clappia_tools/_models/__init__.py
clappia_tools/_models/model.py
clappia_tools/_utils/__init__.py
clappia_tools/_utils/api_utils.py
clappia_tools/_utils/logging_utils.py
clappia_tools/_utils/validators.py
clappia_tools/client/__init__.py
clappia_tools/client/app_definition_client.py
clappia_tools/client/base_client.py
clappia_tools/client/clappia_client.py
clappia_tools/client/submission_client.py
clappia_tools/tests/__init__.py
clappia_tools/tests/integration/__init__.py
clappia_tools/tests/integration/definition/test_tools_definition.py
clappia_tools/tests/integration/submission/test_tools_submission.py
clappia_tools/tests/unit/__init__.py
clappia_tools/tests/unit/definition/test_validators.py
clappia_tools/tests/unit/submission/test_client.py
clappia_tools-0.1.6.dist-info/licenses/LICENSE
clappia_tools-0.1.6.dist-info/METADATA
clappia_tools-0.1.6.dist-info/WHEEL
clappia_tools-0.1.6.dist-info/top_level.txt
clappia_tools-0.1.6.dist-info/RECORD
