Metadata-Version: 2.4
Name: clappia-tools
Version: 0.1.6
Summary: Python client for Clappia API integration
Author-email: Rishabh Verma <rishabh.v@clappia.com>
License: MIT
Project-URL: Homepage, https://github.com/clappia-dev/clappia-tools
Project-URL: Documentation, https://github.com/clappia-dev/clappia-tools#readme
Project-URL: Repository, https://github.com/clappia-dev/clappia-tools.git
Project-URL: Bug Tracker, https://github.com/clappia-dev/clappia-tools/issues
Keywords: clappia,client,mcp,rest-apis,tools,workchat,agents
Classifier: Development Status :: 3 - Alpha
Classifier: Intended Audience :: Developers
Classifier: License :: OSI Approved :: MIT License
Classifier: Operating System :: OS Independent
Classifier: Programming Language :: Python :: 3
Classifier: Programming Language :: Python :: 3.10
Classifier: Programming Language :: Python :: 3.11
Classifier: Programming Language :: Python :: 3.12
Requires-Python: >=3.10
License-File: LICENSE
Requires-Dist: requests>=2.31.0
Requires-Dist: python-dotenv>=1.0.0
Requires-Dist: pydantic>=2.0.0
Requires-Dist: typing-extensions>=4.8.0
Provides-Extra: dev
Requires-Dist: pytest>=7.0.0; extra == "dev"
Requires-Dist: black>=23.0.0; extra == "dev"
Requires-Dist: flake8>=6.0.0; extra == "dev"
Requires-Dist: mypy>=1.0.0; extra == "dev"
Requires-Dist: pre-commit>=3.0.0; extra == "dev"
Provides-Extra: test
Requires-Dist: pytest>=7.0.0; extra == "test"
Requires-Dist: pytest-cov>=4.0.0; extra == "test"
Requires-Dist: pytest-mock>=3.10.0; extra == "test"
Provides-Extra: docs
Requires-Dist: mkdocs>=1.4.0; extra == "docs"
Requires-Dist: mkdocs-material>=9.0.0; extra == "docs"
Dynamic: license-file
